skillos/__init__.py
skillos/api.py
skillos/approval_gate.py
skillos/attachments.py
skillos/authorization.py
skillos/budget.py
skillos/cache.py
skillos/circuit_breaker.py
skillos/cli/__init__.py
skillos/cli/commands/__init__.py
skillos/cli/commands/analysis.py
skillos/cli/commands/core.py
skillos/cli/commands/infra.py
skillos/cli/commands/market.py
skillos/cli/commands/pipeline.py
skillos/cli/commands/skills.py
skillos/cli/main.py
skillos/cli/utils.py
skillos/composition.py
skillos/config.py
skillos/connectors.py
skillos/context_monitor.py
skillos/debugging.py
skillos/execution.py
skillos/execution_planner.py
skillos/experimentation.py
skillos/feedback.py
skillos/flow.py
skillos/health.py
skillos/idempotency.py
skillos/jobs.py
skillos/jwt_auth.py
skillos/kernel/__init__.py
skillos/kernel/base.py
skillos/kernel/factory.py
skillos/kernel/local.py
skillos/marketplace.py
skillos/metrics.py
skillos/mode_selector.py
skillos/notification.py
skillos/optimizer.py
skillos/orchestrator.py
skillos/pipeline.py
skillos/policy_engine.py
skillos/preview_renderer.py
skillos/rate_limit.py
skillos/risk_scorer.py
skillos/routing.py
skillos/routing_cache.py
skillos/scheduler.py
skillos/schedules.py
skillos/sdk.py
skillos/secrets_wizard.py
skillos/session/__init__.py
skillos/session/models.py
skillos/session/store.py
skillos/skills/__init__.py
skillos/skills/budget/usage.json
skillos/skills/deprecation.py
skillos/skills/errors.py
skillos/skills/eval.py
skillos/skills/implementations/__init__.py
skillos/skills/implementations/finance/__init__.py
skillos/skills/implementations/finance/convert_currency.py
skillos/skills/implementations/finance/get_exchange_rates.py
skillos/skills/implementations/finance/track_expenses.py
skillos/skills/implementations/office/__init__.py
skillos/skills/implementations/office/coffee_break.py
skillos/skills/implementations/oysters/__init__.py
skillos/skills/implementations/oysters/calculate_logistics.py
skillos_ai-0.2.3.dist-info/METADATA
skillos_ai-0.2.3.dist-info/WHEEL
skillos_ai-0.2.3.dist-info/entry_points.txt
skillos_ai-0.2.3.dist-info/licenses/LICENSE
skillos_ai-0.2.3.dist-info/RECORD
