Metadata-Version: 2.4
Name: skillos-ai
Version: 0.2.3
Summary: SkillOS MVP scaffold
License-File: LICENSE
Author: Alexey
Requires-Python: >=3.11,<4.0
Classifier: Programming Language :: Python :: 3
Classifier: Programming Language :: Python :: 3.11
Classifier: Programming Language :: Python :: 3.12
Classifier: Programming Language :: Python :: 3.13
Classifier: Programming Language :: Python :: 3.14
Requires-Dist: asyncpg (>=0.29,<0.30)
Requires-Dist: click (>=8.1,<9.0)
Requires-Dist: fastapi (>=0.110,<0.111)
Requires-Dist: httpx (>=0.25,<0.26)
Requires-Dist: psycopg[binary] (>=3.1,<4.0)
Requires-Dist: pydantic (>=2.5,<3.0)
Requires-Dist: python-dotenv (>=1.0,<2.0)
Requires-Dist: pyyaml (>=6.0,<7.0)
Requires-Dist: redis (>=5.0,<6.0)
Requires-Dist: structlog (>=24.1,<25.0)
Requires-Dist: uvicorn (>=0.27,<0.28)
